.stestr.conf
AUTHORS
CONTRIBUTING.rst
ChangeLog
LICENSE
README.rst
babel.cfg
requirements.txt
setup.cfg
setup.py
test-requirements.txt
tox.ini
build-scripts/build-rhel-packages-inner.sh
build-scripts/build-rhel-packages.sh
build-scripts/is_version_bumped.py
build-scripts/openstack_neutron_bsn_lldp.build
build-scripts/openstack_neutron_bsn_lldp_pull_req.build
build-scripts/precheckin.sh
build-scripts/upload_to_pypi.sh
docker/centos8-builder/Dockerfile
neutron_arista_ccf_lldp/__init__.py
neutron_arista_ccf_lldp/arista_ccf_lldp.py
neutron_arista_ccf_lldp/rhlib.py
neutron_arista_ccf_lldp/send_lldp.py
neutron_arista_ccf_lldp.egg-info/PKG-INFO
neutron_arista_ccf_lldp.egg-info/SOURCES.txt
neutron_arista_ccf_lldp.egg-info/dependency_links.txt
neutron_arista_ccf_lldp.egg-info/entry_points.txt
neutron_arista_ccf_lldp.egg-info/not-zip-safe
neutron_arista_ccf_lldp.egg-info/pbr.json
neutron_arista_ccf_lldp.egg-info/requires.txt
neutron_arista_ccf_lldp.egg-info/top_level.txt
neutron_arista_ccf_lldp/tests/__init__.py
neutron_arista_ccf_lldp/tests/base.py
neutron_arista_ccf_lldp/tests/test_neutron_arista_ccf_lldp.py
rhel/neutron-arista-ccf-lldp.service
rhel/neutron-arista-ccf-lldp.spec